setup.py
syntaxis/__init__.py
syntaxis.egg-info/PKG-INFO
syntaxis.egg-info/SOURCES.txt
syntaxis.egg-info/dependency_links.txt
syntaxis.egg-info/top_level.txt