Metadata-Version: 2.1
Name: syntaxis
Version: 0.0.1
Summary: syntaxis
Author: shobrook
Author-email: shobrookj@gmail.com
